nickstoolbox/__init__.py
nickstoolbox-0.1.dist-info/LICENSE
nickstoolbox-0.1.dist-info/METADATA
nickstoolbox-0.1.dist-info/WHEEL
nickstoolbox-0.1.dist-info/top_level.txt
nickstoolbox-0.1.dist-info/RECORD
